libseq
