Metadata-Version: 1.1
Name: libseq
Version: 0.15.0
Summary: A library for reading and writing binary HTS count files.
Home-page: https://github.com/antonybholmes/libseq
Author: Antony B Holmes
Author-email: antony.b.holmes@gmail.com
License: UNKNOWN
Platform: UNKNOWN
Classifier: Programming Language :: Python :: 3
Classifier: License :: OSI Approved :: MIT License
Classifier: Operating System :: OS Independent
